elspais/__init__.py
elspais/__main__.py
elspais/cli.py
elspais/commands/__init__.py
elspais/commands/analyze.py
elspais/commands/changed.py
elspais/commands/config_cmd.py
elspais/commands/edit.py
elspais/commands/hash_cmd.py
elspais/commands/index.py
elspais/commands/init.py
elspais/commands/reformat_cmd.py
elspais/commands/rules_cmd.py
elspais/commands/trace.py
elspais/commands/validate.py
elspais/config/__init__.py
elspais/config/defaults.py
elspais/config/loader.py
elspais/core/__init__.py
elspais/core/content_rules.py
elspais/core/git.py
elspais/core/hasher.py
elspais/core/models.py
elspais/core/parser.py
elspais/core/patterns.py
elspais/core/rules.py
elspais/mcp/__init__.py
elspais/mcp/__main__.py
elspais/mcp/context.py
elspais/mcp/serializers.py
elspais/mcp/server.py
elspais/reformat/__init__.py
elspais/reformat/detector.py
elspais/reformat/hierarchy.py
elspais/reformat/line_breaks.py
elspais/reformat/prompts.py
elspais/reformat/transformer.py
elspais/sponsors/__init__.py
elspais/testing/__init__.py
elspais/testing/config.py
elspais/testing/mapper.py
elspais/testing/result_parser.py
elspais/testing/scanner.py
elspais/trace_view/__init__.py
elspais/trace_view/coverage.py
elspais/trace_view/models.py
elspais/trace_view/scanning.py
elspais/trace_view/generators/__init__.py
elspais/trace_view/generators/base.py
elspais/trace_view/generators/csv.py
elspais/trace_view/generators/markdown.py
elspais/trace_view/html/__init__.py
elspais/trace_view/html/generator.py
elspais/trace_view/html/templates/base.html
elspais/trace_view/html/templates/components/code_viewer_modal.html
elspais/trace_view/html/templates/components/file_picker_modal.html
elspais/trace_view/html/templates/components/legend_modal.html
elspais/trace_view/html/templates/components/review_panel.html
elspais/trace_view/html/templates/partials/review-styles.css
elspais/trace_view/html/templates/partials/scripts.js
elspais/trace_view/html/templates/partials/styles.css
elspais-0.11.2.dist-info/METADATA
elspais-0.11.2.dist-info/WHEEL
elspais-0.11.2.dist-info/entry_points.txt
elspais-0.11.2.dist-info/licenses/LICENSE
elspais-0.11.2.dist-info/RECORD
