Metadata-Version: 2.4
Name: elspais
Version: 0.11.2
Summary: Requirements validation and traceability tools - L-Space connects all libraries
Project-URL: Homepage, https://github.com/anspar/elspais
Project-URL: Documentation, https://github.com/anspar/elspais#readme
Project-URL: Repository, https://github.com/anspar/elspais
Project-URL: Issues, https://github.com/anspar/elspais/issues
Project-URL: Changelog, https://github.com/anspar/elspais/blob/main/CHANGELOG.md
Author-email: Anspar <dev@anspar.io>
License-File: LICENSE
Keywords: documentation,requirements,specifications,traceability,validation
Classifier: Development Status :: 4 - Beta
Classifier: Environment :: Console
Classifier: Intended Audience :: Developers
Classifier: License :: OSI Approved :: MIT License
Classifier: Operating System :: OS Independent
Classifier: Programming Language :: Python :: 3
Classifier: Programming Language :: Python :: 3.9
Classifier: Programming Language :: Python :: 3.10
Classifier: Programming Language :: Python :: 3.11
Classifier: Programming Language :: Python :: 3.12
Classifier: Topic :: Software Development :: Documentation
Classifier: Topic :: Software Development :: Quality Assurance
Classifier: Typing :: Typed
Requires-Python: >=3.9
Provides-Extra: all
Requires-Dist: flask-cors>=4.0; extra == 'all'
Requires-Dist: flask>=2.0; extra == 'all'
Requires-Dist: jinja2>=3.0; extra == 'all'
Requires-Dist: mcp>=1.0; extra == 'all'
Provides-Extra: binary
Requires-Dist: pyinstaller>=6.0; extra == 'binary'
Provides-Extra: dev
Requires-Dist: black>=23.0; extra == 'dev'
Requires-Dist: mypy>=1.0; extra == 'dev'
Requires-Dist: pytest-cov>=4.0; extra == 'dev'
Requires-Dist: pytest>=7.0; extra == 'dev'
Requires-Dist: ruff>=0.1.0; extra == 'dev'
Provides-Extra: mcp
Requires-Dist: mcp>=1.0; extra == 'mcp'
Provides-Extra: trace-review
Requires-Dist: flask-cors>=4.0; extra == 'trace-review'
Requires-Dist: flask>=2.0; extra == 'trace-review'
Requires-Dist: jinja2>=3.0; extra == 'trace-review'
Provides-Extra: trace-view
Requires-Dist: jinja2>=3.0; extra == 'trace-view'
